[
    {
        "date": "2012-12-31",
        "title": "Are You Counting The Wrong Days",
        "file": "2012-12-31-are-you-counting-the-wrong-days.html"
    },
    {
        "date": "2017-04-29",
        "title": "Total Cash Flow Or Total Net Worth How To Maximize Them",
        "file": "2017-04-29-total-cash-flow-or-total-net-worth-how-to-maximize-them.html"
    },
    {
        "date": "2012-12-16",
        "title": "A Day In The Life",
        "file": "2012-12-16-a-day-in-the-life.html"
    },
    {
        "date": "2013-05-06",
        "title": "Apple Bottoms Up",
        "file": "2013-05-06-apple-bottoms-up.html"
    },
    {
        "date": "2014-04-28",
        "title": "America The Good And Bad",
        "file": "2014-04-28-america-the-good-and-bad.html"
    },
    {
        "date": "2013-01-06",
        "title": "The Intermediate Player Challenge",
        "file": "2013-01-06-the-intermediate-player-challenge.html"
    },
    {
        "date": "2013-04-29",
        "title": "The Only Ways To Eliminate Fear",
        "file": "2013-04-29-the-only-ways-to-eliminate-fear.html"
    },
    {
        "date": "2017-01-12",
        "title": "Goals Cause Depression",
        "file": "2017-01-12-goals-cause-depression.html"
    },
    {
        "date": "2014-01-21",
        "title": "A Castle In The Jungle",
        "file": "2014-01-21-a-castle-in-the-jungle.html"
    },
    {
        "date": "2020-10-08",
        "title": "Obscure Post On The Digital Future A Vr World",
        "file": "2020-10-08-obscure-post-on-the-digital-future-a-vr-world.html"
    },
    {
        "date": "2016-02-14",
        "title": "The Life",
        "file": "2016-02-14-the-life.html"
    },
    {
        "date": "2014-08-07",
        "title": "Cash",
        "file": "2014-08-07-cash.html"
    },
    {
        "date": "2013-01-15",
        "title": "Maximizing Your Options In Wall Street",
        "file": "2013-01-15-maximizing-your-options-in-wall-street.html"
    },
    {
        "date": "interview-",
        "title": "A Investment Banking",
        "file": "interview-qa-investment-banking.html"
    },
    {
        "date": "efficiency",
        "title": "Html",
        "file": "efficiency.html"
    },
    {
        "date": "2021-03-27",
        "title": "Book Intro Crypto Starting For The Beginners",
        "file": "2021-03-27-book-intro-crypto-starting-for-the-beginners.html"
    },
    {
        "date": "2017-09-01",
        "title": "Life Changing Items To Be Aware Of As You Get Older",
        "file": "2017-09-01-life-changing-items-to-be-aware-of-as-you-get-older.html"
    },
    {
        "date": "triangle-i",
        "title": "Vesting",
        "file": "triangle-investing.html"
    },
    {
        "date": "2019-01-14",
        "title": "What Should Change Over 10 Years And Qa Announcement",
        "file": "2019-01-14-what-should-change-over-10-years-and-qa-announcement.html"
    },
    {
        "date": "2016-10-29",
        "title": "The Future Of Wall Street",
        "file": "2016-10-29-the-future-of-wall-street.html"
    },
    {
        "date": "2013-05-14",
        "title": "Five Life Truths No One Has The Guts To Tell You",
        "file": "2013-05-14-five-life-truths-no-one-has-the-guts-to-tell-you.html"
    },
    {
        "date": "2018-02-10",
        "title": "Qa Session",
        "file": "2018-02-10-qa-session.html"
    },
    {
        "date": "2021-03-13",
        "title": "The Status Disease",
        "file": "2021-03-13-the-status-disease.html"
    },
    {
        "date": "2013-09-24",
        "title": "Become A Millionaire On Wall Street",
        "file": "2013-09-24-become-a-millionaire-on-wall-street.html"
    },
    {
        "date": "2013-07-27",
        "title": "Find A Mentor",
        "file": "2013-07-27-find-a-mentor.html"
    },
    {
        "date": "2015-04-10",
        "title": "Its All About Taking Losses",
        "file": "2015-04-10-its-all-about-taking-losses.html"
    },
    {
        "date": "2019-05-26",
        "title": "Lifestyle Book Preview Please Add Any Additional Questions Topics",
        "file": "2019-05-26-lifestyle-book-preview-please-add-any-additional-questions-topics.html"
    },
    {
        "date": "2014-05-31",
        "title": "What If Game Was A Category In Jeopardy",
        "file": "2014-05-31-what-if-game-was-a-category-in-jeopardy.html"
    },
    {
        "date": "2018-11-19",
        "title": "November Qa",
        "file": "2018-11-19-november-qa.html"
    },
    {
        "date": "2020-02-05",
        "title": "Investing Lessons From The Tesla Short Disaster",
        "file": "2020-02-05-investing-lessons-from-the-tesla-short-disaster.html"
    },
    {
        "date": "2014-06-17",
        "title": "How Does Average Man Try To Succeed In Life",
        "file": "2014-06-17-how-does-average-man-try-to-succeed-in-life.html"
    },
    {
        "date": "2018-04-14",
        "title": "How Much Is Your Time Worth",
        "file": "2018-04-14-how-much-is-your-time-worth.html"
    },
    {
        "date": "2020-06-08",
        "title": "Avoiding And Going After Tail Events",
        "file": "2020-06-08-avoiding-and-going-after-tail-events.html"
    },
    {
        "date": "2020-07-04",
        "title": "What Is Money Fiat Non Fiat",
        "file": "2020-07-04-what-is-money-fiat-non-fiat.html"
    },
    {
        "date": "2015-04-26",
        "title": "1 Million 10 Years Zero Excuses",
        "file": "2015-04-26-1-million-10-years-zero-excuses.html"
    },
    {
        "date": "2013-04-08",
        "title": "No Marriage Pitchbook Project Two Chainz",
        "file": "2013-04-08-no-marriage-pitchbook-project-two-chainz.html"
    },
    {
        "date": "2016-04-07",
        "title": "Guest Blog Post Controlling Your Habits",
        "file": "2016-04-07-guest-blog-post-controlling-your-habits.html"
    },
    {
        "date": "2014-05-01",
        "title": "The Real Guide To Our College Education System",
        "file": "2014-05-01-the-real-guide-to-our-college-education-system.html"
    },
    {
        "date": "2013-10-09",
        "title": "10 Working Life Truths You Dont Learn From Business School",
        "file": "2013-10-09-10-working-life-truths-you-dont-learn-from-business-school.html"
    },
    {
        "date": "2014-07-25",
        "title": "Everything You Need To Know About Choosing A Career",
        "file": "2014-07-25-everything-you-need-to-know-about-choosing-a-career.html"
    },
    {
        "date": "2020-09-21",
        "title": "The Future Of Money And How To Use It",
        "file": "2020-09-21-the-future-of-money-and-how-to-use-it.html"
    },
    {
        "date": "2014-07-30",
        "title": "How Does A Young Man Make Better Decisions 10 Laws To Remember",
        "file": "2014-07-30-how-does-a-young-man-make-better-decisions-10-laws-to-remember.html"
    },
    {
        "date": "2020-08-12",
        "title": "People Suffer From A Lack Of Prioritization",
        "file": "2020-08-12-people-suffer-from-a-lack-of-prioritization.html"
    },
    {
        "date": "2014-03-18",
        "title": "How To Advance Your Game State Frame And Success",
        "file": "2014-03-18-how-to-advance-your-game-state-frame-and-success.html"
    },
    {
        "date": "2013-01-20",
        "title": "Navigating Wall Street",
        "file": "2013-01-20-navigating-wall-street.html"
    },
    {
        "date": "2015-08-17",
        "title": "How To Play Dumb",
        "file": "2015-08-17-how-to-play-dumb.html"
    },
    {
        "date": "2014-08-12",
        "title": "How To Win",
        "file": "2014-08-12-how-to-win.html"
    },
    {
        "date": "2013-11-06",
        "title": "Thoughts After Recruiting Season",
        "file": "2013-11-06-thoughts-after-recruiting-season.html"
    },
    {
        "date": "2013-06-02",
        "title": "Benefits Of A Wing Woman",
        "file": "2013-06-02-benefits-of-a-wing-woman.html"
    },
    {
        "date": "2016-11-20",
        "title": "Soo We Were Right No Surprise",
        "file": "2016-11-20-soo-we-were-right-no-surprise.html"
    },
    {
        "date": "2018-11-02",
        "title": "Common Money Questions Answers Getting Rich Investing Saving And More",
        "file": "2018-11-02-common-money-questions-answers-getting-rich-investing-saving-and-more.html"
    },
    {
        "date": "2013-11-22",
        "title": "A Working Mans Diet",
        "file": "2013-11-22-a-working-mans-diet.html"
    },
    {
        "date": "2015-01-17",
        "title": "Improving Communication",
        "file": "2015-01-17-improving-communication.html"
    },
    {
        "date": "2012-12-19",
        "title": "Expanding Your Comfort Zone Versus Taking A Risk",
        "file": "2012-12-19-expanding-your-comfort-zone-versus-taking-a-risk.html"
    },
    {
        "date": "2013-04-03",
        "title": "How To Build A Basic Dcf",
        "file": "2013-04-03-how-to-build-a-basic-dcf.html"
    },
    {
        "date": "2014-02-12",
        "title": "Night Game Flow",
        "file": "2014-02-12-night-game-flow.html"
    },
    {
        "date": "2019-01-03",
        "title": "Ownership And Responsibility The Green Light To Making More Money",
        "file": "2019-01-03-ownership-and-responsibility-the-green-light-to-making-more-money.html"
    },
    {
        "date": "2013-09-05",
        "title": "Game For Asian Guys",
        "file": "2013-09-05-game-for-asian-guys.html"
    },
    {
        "date": "2020-09-07",
        "title": "Ignore What People Say Focus On What They Do Specific Examples",
        "file": "2020-09-07-ignore-what-people-say-focus-on-what-they-do-specific-examples.html"
    },
    {
        "date": "2017-03-04",
        "title": "Making Money In A Trump Environment",
        "file": "2017-03-04-making-money-in-a-trump-environment.html"
    },
    {
        "date": "2020-02-17",
        "title": "Parasite Movie Spoilers Metaphors Etc",
        "file": "2020-02-17-parasite-movie-spoilers-metaphors-etc.html"
    },
    {
        "date": "2015-02-23",
        "title": "How To Pick Up A Sexy Latina",
        "file": "2015-02-23-how-to-pick-up-a-sexy-latina.html"
    },
    {
        "date": "2017-09-09",
        "title": "Spotting The Mediocre Ten Common Types",
        "file": "2017-09-09-spotting-the-mediocre-ten-common-types.html"
    },
    {
        "date": "2013-08-12",
        "title": "How To Break The Golden Handcuffs",
        "file": "2013-08-12-how-to-break-the-golden-handcuffs.html"
    },
    {
        "date": "2017-01-09",
        "title": "Financial Samurai Paid Up And What We Think Trump Does",
        "file": "2017-01-09-financial-samurai-paid-up-and-what-we-think-trump-does.html"
    },
    {
        "date": "2018-12-20",
        "title": "Wall Street",
        "file": "2018-12-20-wall-street.html"
    },
    {
        "date": "2018-02-27",
        "title": "The Five Rigged Games In Life",
        "file": "2018-02-27-the-five-rigged-games-in-life.html"
    },
    {
        "date": "2017-05-14",
        "title": "Maximizing Retirement Accounts And Why They Will Be Meaningless To You",
        "file": "2017-05-14-maximizing-retirement-accounts-and-why-they-will-be-meaningless-to-you.html"
    },
    {
        "date": "2020-05-25",
        "title": "For New Readers Please Read",
        "file": "2020-05-25-for-new-readers-please-read.html"
    },
    {
        "date": "2015-07-18",
        "title": "10 Free Copies Of Gorilla Mindset",
        "file": "2015-07-18-10-free-copies-of-gorilla-mindset.html"
    },
    {
        "date": "2017-11-24",
        "title": "Qa Is Open And Why We Are More Aggressive With Portfolio Mangement",
        "file": "2017-11-24-qa-is-open-and-why-we-are-more-aggressive-with-portfolio-mangement.html"
    },
    {
        "date": "2020-06-01",
        "title": "Quick Update Post The Riots And Re Opening",
        "file": "2020-06-01-quick-update-post-the-riots-and-re-opening.html"
    },
    {
        "date": "2014-12-07",
        "title": "Basic Overview Consumer",
        "file": "2014-12-07-basic-overview-consumer.html"
    },
    {
        "date": "2013-04-22",
        "title": "Choosing Friends",
        "file": "2013-04-22-choosing-friends.html"
    },
    {
        "date": "2014-07-14",
        "title": "A Detailed Look At Technology Media And Telecom Tmt Part 2 Of 2",
        "file": "2014-07-14-a-detailed-look-at-technology-media-and-telecom-tmt-part-2-of-2.html"
    },
    {
        "date": "2017-05-26",
        "title": "How To Use Big Gains Vs Small Gains Make The Big Moves Early",
        "file": "2017-05-26-how-to-use-big-gains-vs-small-gains-make-the-big-moves-early.html"
    },
    {
        "date": "2017-07-12",
        "title": "How To Create A Robot",
        "file": "2017-07-12-how-to-create-a-robot.html"
    },
    {
        "date": "2017-12-10",
        "title": "What Happens When You Execute With Efficiency",
        "file": "2017-12-10-what-happens-when-you-execute-with-efficiency.html"
    },
    {
        "date": "2020-08-29",
        "title": "Significantly Improving Personal Productivity",
        "file": "2020-08-29-significantly-improving-personal-productivity.html"
    },
    {
        "date": "2015-05-18",
        "title": "Analysis Paralysis Damaging Your Net Worth And Future",
        "file": "2015-05-18-analysis-paralysis-damaging-your-net-worth-and-future.html"
    },
    {
        "date": "2013-04-11",
        "title": "Dont Dilute Yourself The Importance Of Becoming Recognized At Your Favorite Bar",
        "file": "2013-04-11-dont-dilute-yourself-the-importance-of-becoming-recognized-at-your-favorite-bar.html"
    },
    {
        "date": "2013-03-24",
        "title": "Unlock Your Mind",
        "file": "2013-03-24-unlock-your-mind.html"
    },
    {
        "date": "2017-12-16",
        "title": "Ludvig Sunstrom And Mikael Syding Present Breaking Out Of Homeostasis",
        "file": "2017-12-16-ludvig-sunstrom-and-mikael-syding-present-breaking-out-of-homeostasis.html"
    },
    {
        "date": "2020-08-28",
        "title": "Short Qa Here",
        "file": "2020-08-28-short-qa-here.html"
    },
    {
        "date": "2015-03-16",
        "title": "Best Real Estate Investment Buy The Building",
        "file": "2015-03-16-best-real-estate-investment-buy-the-building.html"
    },
    {
        "date": "2021-03-29",
        "title": "Rotating Clown Ad Times Square",
        "file": "2021-03-29-rotating-clown-ad-times-square.html"
    },
    {
        "date": "2019-05-03",
        "title": "American Cults And Subjects That Stir Up Emotion",
        "file": "2019-05-03-american-cults-and-subjects-that-stir-up-emotion.html"
    },
    {
        "date": "2017-12-13",
        "title": "Investment Banking Compensation 2017 An Up Year",
        "file": "2017-12-13-investment-banking-compensation-2017-an-up-year.html"
    },
    {
        "date": "2014-03-24",
        "title": "Passive Income",
        "file": "2014-03-24-passive-income.html"
    },
    {
        "date": "2013-05-21",
        "title": "Basic Guide To Valuation And Metrics By Sector",
        "file": "2013-05-21-basic-guide-to-valuation-and-metrics-by-sector.html"
    },
    {
        "date": "2018-03-07",
        "title": "Avoiding The Success Pitfalls",
        "file": "2018-03-07-avoiding-the-success-pitfalls.html"
    },
    {
        "date": "2020-02-27",
        "title": "Covid 19 Update Easy Solutions For Big Problems",
        "file": "2020-02-27-covid-19-update-easy-solutions-for-big-problems.html"
    },
    {
        "date": "2020-09-28",
        "title": "What Isnt Going To Change And Qa Announcement",
        "file": "2020-09-28-what-isnt-going-to-change-and-qa-announcement.html"
    },
    {
        "date": "2013-06-11",
        "title": "Basics To Personal Debt",
        "file": "2013-06-11-basics-to-personal-debt.html"
    },
    {
        "date": "2015-12-19",
        "title": "Investment Banking Compensation 2015",
        "file": "2015-12-19-investment-banking-compensation-2015.html"
    },
    {
        "date": "2014-07-07",
        "title": "Guideline For A Healthy Relationship With A Sexy Woman",
        "file": "2014-07-07-guideline-for-a-healthy-relationship-with-a-sexy-woman.html"
    },
    {
        "date": "2013-09-22",
        "title": "Basic Guide To Dividend Investing Always Avoid Taxes",
        "file": "2013-09-22-basic-guide-to-dividend-investing-always-avoid-taxes.html"
    },
    {
        "date": "2013-08-29",
        "title": "20 Rules For Your Twenties",
        "file": "2013-08-29-20-rules-for-your-twenties.html"
    },
    {
        "date": "2017-12-22",
        "title": "Ask Your Crypto Related Questions",
        "file": "2017-12-22-ask-your-crypto-related-questions.html"
    },
    {
        "date": "2014-10-19",
        "title": "Are You A Time Waster",
        "file": "2014-10-19-are-you-a-time-waster.html"
    },
    {
        "date": "2014-05-19",
        "title": "Game Back To The Basics",
        "file": "2014-05-19-game-back-to-the-basics.html"
    },
    {
        "date": "2014-03-01",
        "title": "Six Life Lessons From Video Games",
        "file": "2014-03-01-six-life-lessons-from-video-games.html"
    },
    {
        "date": "2016-03-19",
        "title": "Donald Trump Brand Part 2",
        "file": "2016-03-19-donald-trump-brand-part-2.html"
    },
    {
        "date": "2017-07-31",
        "title": "Follow The Hate And Youll Find The Truth",
        "file": "2017-07-31-follow-the-hate-and-youll-find-the-truth.html"
    },
    {
        "date": "2014-11-23",
        "title": "Studying Advice",
        "file": "2014-11-23-studying-advice.html"
    },
    {
        "date": "approved-p",
        "title": "Oducts",
        "file": "approved-products.html"
    },
    {
        "date": "2017-10-12",
        "title": "Everything Comes Down To Ego Feed It To Get What You Want",
        "file": "2017-10-12-everything-comes-down-to-ego-feed-it-to-get-what-you-want.html"
    },
    {
        "date": "2015-04-26",
        "title": "Personal Finance",
        "file": "2015-04-26-personal-finance.html"
    },
    {
        "date": "2017-05-30",
        "title": "Is Starting A Company The Least Risky Option To Get Rich",
        "file": "2017-05-30-is-starting-a-company-the-least-risky-option-to-get-rich.html"
    },
    {
        "date": "2015-01-01",
        "title": "Overview Of The Oil And Gas Sector",
        "file": "2015-01-01-overview-of-the-oil-and-gas-sector.html"
    },
    {
        "date": "2014-03-14",
        "title": "Random Thoughts On The Millennial Generation",
        "file": "2014-03-14-random-thoughts-on-the-millennial-generation.html"
    },
    {
        "date": "2013-05-17",
        "title": "Become A Minimalist Dont Be Frugal",
        "file": "2013-05-17-become-a-minimalist-dont-be-frugal.html"
    },
    {
        "date": "2017-12-04",
        "title": "Quality Of Life And Time 15 Things To Remember",
        "file": "2017-12-04-quality-of-life-and-time-15-things-to-remember.html"
    },
    {
        "date": "top-posts.",
        "title": "Tml",
        "file": "top-posts.html"
    },
    {
        "date": "2015-01-04",
        "title": "The Definitive Guide To Doing The Opposite",
        "file": "2015-01-04-the-definitive-guide-to-doing-the-opposite.html"
    },
    {
        "date": "2013-06-10",
        "title": "Basic Guide To Understanding A Stock Facebook Example",
        "file": "2013-06-10-basic-guide-to-understanding-a-stock-facebook-example.html"
    },
    {
        "date": "2013-06-08",
        "title": "Review Of Choose Yourself",
        "file": "2013-06-08-review-of-choose-yourself.html"
    },
    {
        "date": "2014-01-31",
        "title": "How To Invest As A Bachelor",
        "file": "2014-01-31-how-to-invest-as-a-bachelor.html"
    },
    {
        "date": "2016-04-18",
        "title": "Money Changes Your Life",
        "file": "2016-04-18-money-changes-your-life.html"
    },
    {
        "date": "2015-09-13",
        "title": "Random Musings And A Stream Of Consciousness",
        "file": "2015-09-13-random-musings-and-a-stream-of-consciousness.html"
    },
    {
        "date": "2013-03-03",
        "title": "How To Spot A Liar",
        "file": "2013-03-03-how-to-spot-a-liar.html"
    },
    {
        "date": "2017-06-17",
        "title": "The Greatest Time In History To Be Alive",
        "file": "2017-06-17-the-greatest-time-in-history-to-be-alive.html"
    },
    {
        "date": "2013-11-27",
        "title": "Cliff Notes For Evaluating A City",
        "file": "2013-11-27-cliff-notes-for-evaluating-a-city.html"
    },
    {
        "date": "2016-05-31",
        "title": "End Of The Road What To Expect And How To Spot Them",
        "file": "2016-05-31-end-of-the-road-what-to-expect-and-how-to-spot-them.html"
    },
    {
        "date": "2018-04-09",
        "title": "Predictions For The Future",
        "file": "2018-04-09-predictions-for-the-future.html"
    },
    {
        "date": "2019-02-05",
        "title": "A Basic Post On Minimum Leverage And Several Announcements",
        "file": "2019-02-05-a-basic-post-on-minimum-leverage-and-several-announcements.html"
    },
    {
        "date": "2018-11-04",
        "title": "Common Social Tells In 2018",
        "file": "2018-11-04-common-social-tells-in-2018.html"
    },
    {
        "date": "2017-05-16",
        "title": "The Five Stages Of Earning Income",
        "file": "2017-05-16-the-five-stages-of-earning-income.html"
    },
    {
        "date": "2020-06-20",
        "title": "Short Qa Is Here 2",
        "file": "2020-06-20-short-qa-is-here-2.html"
    },
    {
        "date": "2013-02-08",
        "title": "The Only Four Things That Matter",
        "file": "2013-02-08-the-only-four-things-that-matter.html"
    },
    {
        "date": "2014-03-31",
        "title": "Are You Spending Too Much Time On Game Take The Quiz",
        "file": "2014-03-31-are-you-spending-too-much-time-on-game-take-the-quiz.html"
    },
    {
        "date": "2015-04-20",
        "title": "Wallstreetplayboys.Com",
        "file": "2015-04-20-wallstreetplayboys.com.html"
    },
    {
        "date": "2013-07-16",
        "title": "Best Of Eddie Volume 1",
        "file": "2013-07-16-best-of-eddie-volume-1.html"
    },
    {
        "date": "2018-04-14",
        "title": "Qa Is Here",
        "file": "2018-04-14-qa-is-here.html"
    },
    {
        "date": "2013-12-08",
        "title": "10 Ways To Evolve Your Game",
        "file": "2013-12-08-10-ways-to-evolve-your-game.html"
    },
    {
        "date": "2014-04-14",
        "title": "A Day In The Life Hedge Fund Associate Edition",
        "file": "2014-04-14-a-day-in-the-life-hedge-fund-associate-edition.html"
    },
    {
        "date": "2020-10-01",
        "title": "Investing Qa",
        "file": "2020-10-01-investing-qa.html"
    },
    {
        "date": "2019-06-24",
        "title": "Personal Finance",
        "file": "2019-06-24-personal-finance.html"
    },
    {
        "date": "2016-01-01",
        "title": "Bold Prediction President Donald J Trump",
        "file": "2016-01-01-bold-prediction-president-donald-j-trump.html"
    },
    {
        "date": "2013-10-16",
        "title": "Start Talking To Yourself Today",
        "file": "2013-10-16-start-talking-to-yourself-today.html"
    },
    {
        "date": "2021-04-14",
        "title": "Banks Are Zeros April 27 2021 And The End Of This Website",
        "file": "2021-04-14-banks-are-zeros-april-27-2021-and-the-end-of-this-website.html"
    },
    {
        "date": "2017-06-12",
        "title": "Efficient Market Hypothesis Does Not Make Logical Sense",
        "file": "2017-06-12-efficient-market-hypothesis-does-not-make-logical-sense.html"
    },
    {
        "date": "2017-03-07",
        "title": "How Much Should You Be Worth Many Paths To Becoming A Multi Millionaire",
        "file": "2017-03-07-how-much-should-you-be-worth-many-paths-to-becoming-a-multi-millionaire.html"
    },
    {
        "date": "2016-03-20",
        "title": "New York Vs San Francisco Landslide For New York City",
        "file": "2016-03-20-new-york-vs-san-francisco-landslide-for-new-york-city.html"
    },
    {
        "date": "2017-03-16",
        "title": "Explaining The Warren Buffet Bet Passive Vs Active And What To Do About It",
        "file": "2017-03-16-explaining-the-warren-buffet-bet-passive-vs-active-and-what-to-do-about-it.html"
    },
    {
        "date": "2014-10-19",
        "title": "8 Takeaways Brief Hangout With Mike Cernovich Danger And Play",
        "file": "2014-10-19-8-takeaways-brief-hangout-with-mike-cernovich-danger-and-play.html"
    },
    {
        "date": "2016-07-25",
        "title": "Physical Commodity Trading Guest Post",
        "file": "2016-07-25-physical-commodity-trading-guest-post.html"
    },
    {
        "date": "2013-04-05",
        "title": "Building Unbreakable Confidence",
        "file": "2013-04-05-building-unbreakable-confidence.html"
    },
    {
        "date": "2013-04-07",
        "title": "So You Want To Be A Trader",
        "file": "2013-04-07-so-you-want-to-be-a-trader.html"
    },
    {
        "date": "2014-04-04",
        "title": "How To Prepare For Your Investment Banking Analyst Job The Truth",
        "file": "2014-04-04-how-to-prepare-for-your-investment-banking-analyst-job-the-truth.html"
    },
    {
        "date": "2020-02-05",
        "title": "Wall Street",
        "file": "2020-02-05-wall-street.html"
    },
    {
        "date": "2018-10-21",
        "title": "Wall Street Past Present And Future",
        "file": "2018-10-21-wall-street-past-present-and-future.html"
    },
    {
        "date": "2013-10-18",
        "title": "Wallstreetplayboys Success Stories Start Rolling In",
        "file": "2013-10-18-wallstreetplayboys-success-stories-start-rolling-in.html"
    },
    {
        "date": "2015-04-24",
        "title": "Overview Of Leveraged Finance",
        "file": "2015-04-24-overview-of-leveraged-finance.html"
    },
    {
        "date": "2013-01-14",
        "title": "Resume Template",
        "file": "2013-01-14-resume-template.html"
    },
    {
        "date": "2014-03-10",
        "title": "Im A Failure",
        "file": "2014-03-10-im-a-failure.html"
    },
    {
        "date": "2015-04-13",
        "title": "What Type Of Intelligence Do You Have",
        "file": "2015-04-13-what-type-of-intelligence-do-you-have.html"
    },
    {
        "date": "2020-08-23",
        "title": "Some Fun Social Tells And Qa Announcement",
        "file": "2020-08-23-some-fun-social-tells-and-qa-announcement.html"
    },
    {
        "date": "2014-02-23",
        "title": "High Risk Investments",
        "file": "2014-02-23-high-risk-investments.html"
    },
    {
        "date": "2014-01-10",
        "title": "Cfa Or Mba What Pays More",
        "file": "2014-01-10-cfa-or-mba-what-pays-more.html"
    },
    {
        "date": "2013-04-29",
        "title": "Personal Finance College Student No Debt",
        "file": "2013-04-29-personal-finance-college-student-no-debt.html"
    },
    {
        "date": "2014-12-11",
        "title": "Personal Finance Advice On The Internet Is Bogus",
        "file": "2014-12-11-personal-finance-advice-on-the-internet-is-bogus.html"
    },
    {
        "date": "2014-07-22",
        "title": "20 Things You Should Realize After 1 Year On The Job",
        "file": "2014-07-22-20-things-you-should-realize-after-1-year-on-the-job.html"
    },
    {
        "date": "2014-11-30",
        "title": "Message To The Financially Independent",
        "file": "2014-11-30-message-to-the-financially-independent.html"
    },
    {
        "date": "2014-10-06",
        "title": "How Do You Get Rich Two Rules",
        "file": "2014-10-06-how-do-you-get-rich-two-rules.html"
    },
    {
        "date": "2021-03-23",
        "title": "Reminder Post Rig The System In Your Favor",
        "file": "2021-03-23-reminder-post-rig-the-system-in-your-favor.html"
    },
    {
        "date": "2014-09-07",
        "title": "Weekly Workout Routine",
        "file": "2014-09-07-weekly-workout-routine.html"
    },
    {
        "date": "2014-10-25",
        "title": "The Downside To Blogging",
        "file": "2014-10-25-the-downside-to-blogging.html"
    },
    {
        "date": "2015-12-30",
        "title": "How To Have A Killer New Years Eve",
        "file": "2015-12-30-how-to-have-a-killer-new-years-eve.html"
    },
    {
        "date": "2015-11-01",
        "title": "Simple Examples Of Thinking Differently",
        "file": "2015-11-01-simple-examples-of-thinking-differently.html"
    },
    {
        "date": "2014-11-13",
        "title": "Work Life Balance",
        "file": "2014-11-13-work-life-balance.html"
    },
    {
        "date": "2019-02-10",
        "title": "Guest Post Ed Latimores Financial Journey",
        "file": "2019-02-10-guest-post-ed-latimores-financial-journey.html"
    },
    {
        "date": "2017-04-26",
        "title": "Risk Adjusted Financial Independence Nothing Is Guaranteed Including Government Bonds",
        "file": "2017-04-26-risk-adjusted-financial-independence-nothing-is-guaranteed-including-government-bonds.html"
    },
    {
        "date": "2013-03-11",
        "title": "What Group To Join Hint Ecmdcm Is For Suckers",
        "file": "2013-03-11-what-group-to-join-hint-ecmdcm-is-for-suckers.html"
    },
    {
        "date": "2019-06-03",
        "title": "Wallstreetplayboys.Com",
        "file": "2019-06-03-wallstreetplayboys.com.html"
    },
    {
        "date": "2014-09-24",
        "title": "You Dont Want To Sell Too Bad",
        "file": "2014-09-24-you-dont-want-to-sell-too-bad.html"
    },
    {
        "date": "2017-08-14",
        "title": "How To Quit When Throwing In The Towel Is The Right Decision",
        "file": "2017-08-14-how-to-quit-when-throwing-in-the-towel-is-the-right-decision.html"
    },
    {
        "date": "2015-02-02",
        "title": "How To Live A Balanced Life",
        "file": "2015-02-02-how-to-live-a-balanced-life.html"
    },
    {
        "date": "2015-06-14",
        "title": "What Is A Regular Person",
        "file": "2015-06-14-what-is-a-regular-person.html"
    },
    {
        "date": "2013-10-25",
        "title": "What Is Game",
        "file": "2013-10-25-what-is-game.html"
    },
    {
        "date": "2019-06-03",
        "title": "Success",
        "file": "2019-06-03-success.html"
    },
    {
        "date": "2020-08-15",
        "title": "Success",
        "file": "2020-08-15-success.html"
    },
    {
        "date": "2018-04-02",
        "title": "Adjusting Your Net Worth And Preparing For Downturns",
        "file": "2018-04-02-adjusting-your-net-worth-and-preparing-for-downturns.html"
    },
    {
        "date": "2017-05-07",
        "title": "The Secret For Success In Life Being Wrong Early",
        "file": "2017-05-07-the-secret-for-success-in-life-being-wrong-early.html"
    },
    {
        "date": "2019-05-20",
        "title": "Personal Finance",
        "file": "2019-05-20-personal-finance.html"
    },
    {
        "date": "2015-02-17",
        "title": "The Power Of 1 And Why You Dont Blog For Money",
        "file": "2015-02-17-the-power-of-1-and-why-you-dont-blog-for-money.html"
    },
    {
        "date": "2020-02-03",
        "title": "Quick Math To Keep You Focused On Your Side Hustle",
        "file": "2020-02-03-quick-math-to-keep-you-focused-on-your-side-hustle.html"
    },
    {
        "date": "2018-10-25",
        "title": "October Qa Is Here",
        "file": "2018-10-25-october-qa-is-here.html"
    },
    {
        "date": "2020-07-24",
        "title": "Qa Is Here 13",
        "file": "2020-07-24-qa-is-here-13.html"
    },
    {
        "date": "2019-01-18",
        "title": "January Qa Is Here",
        "file": "2019-01-18-january-qa-is-here.html"
    },
    {
        "date": "start-here",
        "title": "Html",
        "file": "start-here.html"
    },
    {
        "date": "2013-05-15",
        "title": "Top 8 Losers You Will Meet In Real Life",
        "file": "2013-05-15-top-8-losers-you-will-meet-in-real-life.html"
    },
    {
        "date": "2015-03-29",
        "title": "Application Of Logic To Improve Your Life",
        "file": "2015-03-29-application-of-logic-to-improve-your-life.html"
    },
    {
        "date": "2013-01-30",
        "title": "So You Just Got Hired Revisited",
        "file": "2013-01-30-so-you-just-got-hired-revisited.html"
    },
    {
        "date": "2015-03-01",
        "title": "How To Remain Happy At All Times",
        "file": "2015-03-01-how-to-remain-happy-at-all-times.html"
    },
    {
        "date": "2017-10-21",
        "title": "Getting Rich And Laying Low",
        "file": "2017-10-21-getting-rich-and-laying-low.html"
    },
    {
        "date": "2015-04-20",
        "title": "Personal Finance And Dating",
        "file": "2015-04-20-personal-finance-and-dating.html"
    },
    {
        "date": "2019-06-11",
        "title": "Success",
        "file": "2019-06-11-success.html"
    },
    {
        "date": "frequently",
        "title": "Asked Questions",
        "file": "frequently-asked-questions.html"
    },
    {
        "date": "2014-03-12",
        "title": "Networking For Hedge Fund Interviews Its Unstructured",
        "file": "2014-03-12-networking-for-hedge-fund-interviews-its-unstructured.html"
    },
    {
        "date": "2017-02-06",
        "title": "Creating Focus",
        "file": "2017-02-06-creating-focus.html"
    },
    {
        "date": "2016-07-09",
        "title": "Calculating Individual Total Worth",
        "file": "2016-07-09-calculating-individual-total-worth.html"
    },
    {
        "date": "2017-05-20",
        "title": "Watch The Company Man Give Away His Life",
        "file": "2017-05-20-watch-the-company-man-give-away-his-life.html"
    },
    {
        "date": "2020-10-24",
        "title": "The Growing Economic Divide",
        "file": "2020-10-24-the-growing-economic-divide.html"
    },
    {
        "date": "2020-10-13",
        "title": "Adapt Or Die Some Things Wont Be Like The Past",
        "file": "2020-10-13-adapt-or-die-some-things-wont-be-like-the-past.html"
    },
    {
        "date": "2018-12-03",
        "title": "Everything Has A Good And Bad Side Including Money",
        "file": "2018-12-03-everything-has-a-good-and-bad-side-including-money.html"
    },
    {
        "date": "2013-09-19",
        "title": "What Information Do You Need",
        "file": "2013-09-19-what-information-do-you-need.html"
    },
    {
        "date": "2019-04-21",
        "title": "Life Is Just A Game Of Tweaks And Personal Talent",
        "file": "2019-04-21-life-is-just-a-game-of-tweaks-and-personal-talent.html"
    },
    {
        "date": "2017-10-29",
        "title": "The Next Big Market And The Underlying Truth About The Brain",
        "file": "2017-10-29-the-next-big-market-and-the-underlying-truth-about-the-brain.html"
    },
    {
        "date": "2019-04-16",
        "title": "Attempt At Valuing Time Over 2 Decades And Qa Announcement",
        "file": "2019-04-16-attempt-at-valuing-time-over-2-decades-and-qa-announcement.html"
    },
    {
        "date": "2013-08-02",
        "title": "Sp 500 Surpasses 1700 The World Is Not Ending",
        "file": "2013-08-02-sp-500-surpasses-1700-the-world-is-not-ending.html"
    },
    {
        "date": "2013-05-12",
        "title": "No One Cares About You",
        "file": "2013-05-12-no-one-cares-about-you.html"
    },
    {
        "date": "2018-04-23",
        "title": "Get Rid Of Jealousy Hatred And Stress By Thinking In Multiple Dimensions",
        "file": "2018-04-23-get-rid-of-jealousy-hatred-and-stress-by-thinking-in-multiple-dimensions.html"
    },
    {
        "date": "2014-04-09",
        "title": "Why And How To Keep A Journal",
        "file": "2014-04-09-why-and-how-to-keep-a-journal.html"
    },
    {
        "date": "2015-04-26",
        "title": "Success",
        "file": "2015-04-26-success.html"
    },
    {
        "date": "2018-02-04",
        "title": "Spending Money To Maximize Life",
        "file": "2018-02-04-spending-money-to-maximize-life.html"
    },
    {
        "date": "2020-06-29",
        "title": "The Divide Short Predictions And An Answer To The Inflation Question",
        "file": "2020-06-29-the-divide-short-predictions-and-an-answer-to-the-inflation-question.html"
    },
    {
        "date": "2017-07-01",
        "title": "Buying Time From Low Income All The Way Up To High Income",
        "file": "2017-07-01-buying-time-from-low-income-all-the-way-up-to-high-income.html"
    },
    {
        "date": "2021-04-06",
        "title": "It Is The Year 2035 Questions Welcome",
        "file": "2021-04-06-it-is-the-year-2035-questions-welcome.html"
    },
    {
        "date": "2015-03-16",
        "title": "Wall Street",
        "file": "2015-03-16-wall-street.html"
    },
    {
        "date": "2017-07-09",
        "title": "Gambling Like A Boss Always Bet On Black",
        "file": "2017-07-09-gambling-like-a-boss-always-bet-on-black.html"
    },
    {
        "date": "2017-11-05",
        "title": "When To Sell Your First Company Part 1",
        "file": "2017-11-05-when-to-sell-your-first-company-part-1.html"
    },
    {
        "date": "2016-01-16",
        "title": "Follow Your Skills Not Your Dreams",
        "file": "2016-01-16-follow-your-skills-not-your-dreams.html"
    },
    {
        "date": "2016-01-04",
        "title": "New Year Book Reviews",
        "file": "2016-01-04-new-year-book-reviews.html"
    },
    {
        "date": "2015-12-13",
        "title": "The Brutal Truth About Friends",
        "file": "2015-12-13-the-brutal-truth-about-friends.html"
    },
    {
        "date": "2013-06-04",
        "title": "Cover Letter",
        "file": "2013-06-04-cover-letter.html"
    },
    {
        "date": "2014-10-02",
        "title": "Overview Of Healthcare Part 1",
        "file": "2014-10-02-overview-of-healthcare-part-1.html"
    },
    {
        "date": "2017-08-27",
        "title": "Mayweather Mcgregor Fight Business Tutorial And Controversial Lessons",
        "file": "2017-08-27-mayweather-mcgregor-fight-business-tutorial-and-controversial-lessons.html"
    },
    {
        "date": "2018-12-27",
        "title": "December Qa Is Here",
        "file": "2018-12-27-december-qa-is-here.html"
    },
    {
        "date": "2014-11-23",
        "title": "Dont Focus On Net Worth Focus On Adjusted Liftime Spend Als",
        "file": "2014-11-23-dont-focus-on-net-worth-focus-on-adjusted-liftime-spend-als.html"
    },
    {
        "date": "2013-11-20",
        "title": "Overcoming Depression",
        "file": "2013-11-20-overcoming-depression.html"
    },
    {
        "date": "2014-06-28",
        "title": "A Detailed Look At Technology Media And Telecom Tmt Part 1 Of 2",
        "file": "2014-06-28-a-detailed-look-at-technology-media-and-telecom-tmt-part-1-of-2.html"
    },
    {
        "date": "2016-09-11",
        "title": "Book Introduction Efficiency",
        "file": "2016-09-11-book-introduction-efficiency.html"
    },
    {
        "date": "2017-08-22",
        "title": "Spotting The Fool In The Room",
        "file": "2017-08-22-spotting-the-fool-in-the-room.html"
    },
    {
        "date": "2017-11-19",
        "title": "Qa Announcement And Introduction To Personal Finance Book",
        "file": "2017-11-19-qa-announcement-and-introduction-to-personal-finance-book.html"
    },
    {
        "date": "2014-05-28",
        "title": "Dating Life For The Average Man In America",
        "file": "2014-05-28-dating-life-for-the-average-man-in-america.html"
    },
    {
        "date": "2013-05-26",
        "title": "Informational Interview Guide",
        "file": "2013-05-26-informational-interview-guide.html"
    },
    {
        "date": "2019-01-20",
        "title": "Solving Some Rich People Problems",
        "file": "2019-01-20-solving-some-rich-people-problems.html"
    },
    {
        "date": "2013-03-28",
        "title": "A Day In The Life Of A Loser",
        "file": "2013-03-28-a-day-in-the-life-of-a-loser.html"
    },
    {
        "date": "2014-01-15",
        "title": "10 Ways To Change Your Life Today",
        "file": "2014-01-15-10-ways-to-change-your-life-today.html"
    },
    {
        "date": "2012-12-24",
        "title": "Wall Street Dating Economics",
        "file": "2012-12-24-wall-street-dating-economics.html"
    },
    {
        "date": "2017-02-22",
        "title": "Deflect Or Agree With Everything A Huge Time Saver With Regular People",
        "file": "2017-02-22-deflect-or-agree-with-everything-a-huge-time-saver-with-regular-people.html"
    },
    {
        "date": "2014-05-13",
        "title": "Quick Guide To Building Maintaining And Ending Relationships",
        "file": "2014-05-13-quick-guide-to-building-maintaining-and-ending-relationships.html"
    },
    {
        "date": "2017-09-15",
        "title": "Enterprise Sales A Legitimate Career To Get Rich",
        "file": "2017-09-15-enterprise-sales-a-legitimate-career-to-get-rich.html"
    },
    {
        "date": "2017-04-27",
        "title": "Investment Banking Verticals Product Groups Increasing Your Wage And Bonus",
        "file": "2017-04-27-investment-banking-verticals-product-groups-increasing-your-wage-and-bonus.html"
    },
    {
        "date": "2015-03-09",
        "title": "How Does This Blog Operate",
        "file": "2015-03-09-how-does-this-blog-operate.html"
    },
    {
        "date": "2018-11-25",
        "title": "Think Like Youre In The 1 Focus Energy On Important Questions",
        "file": "2018-11-25-think-like-youre-in-the-1-focus-energy-on-important-questions.html"
    },
    {
        "date": "2017-07-22",
        "title": "Efficiency Is Now Up",
        "file": "2017-07-22-efficiency-is-now-up.html"
    },
    {
        "date": "2020-02-09",
        "title": "Qa Is Here 8",
        "file": "2020-02-09-qa-is-here-8.html"
    },
    {
        "date": "2018-05-11",
        "title": "The Five Ways To Evaluate A City",
        "file": "2018-05-11-the-five-ways-to-evaluate-a-city.html"
    },
    {
        "date": "2018-03-19",
        "title": "Money How Much Is Enough",
        "file": "2018-03-19-money-how-much-is-enough.html"
    },
    {
        "date": "2012-12-18",
        "title": "Breaking Into Venture Capital",
        "file": "2012-12-18-breaking-into-venture-capital.html"
    },
    {
        "date": "2021-03-20",
        "title": "Musings From Nearly A Decade Of Blogging",
        "file": "2021-03-20-musings-from-nearly-a-decade-of-blogging.html"
    },
    {
        "date": "2018-11-10",
        "title": "Thinking About Investing And Risk",
        "file": "2018-11-10-thinking-about-investing-and-risk.html"
    },
    {
        "date": "2018-12-27",
        "title": "Investing 10 Doesnt Work Run The Numbers Get Rich Fast Instead",
        "file": "2018-12-27-investing-10-doesnt-work-run-the-numbers-get-rich-fast-instead.html"
    },
    {
        "date": "2018-04-18",
        "title": "Four Levels Of Financial Independence For A Single Person",
        "file": "2018-04-18-four-levels-of-financial-independence-for-a-single-person.html"
    },
    {
        "date": "2015-07-11",
        "title": "Guest Post Game And Business Intersections",
        "file": "2015-07-11-guest-post-game-and-business-intersections.html"
    },
    {
        "date": "2020-08-15",
        "title": "What Is Decentralized Finance And Yield Farming Easy Quick Read",
        "file": "2020-08-15-what-is-decentralized-finance-and-yield-farming-easy-quick-read.html"
    },
    {
        "date": "2017-08-07",
        "title": "Time To Manage Your Own Book",
        "file": "2017-08-07-time-to-manage-your-own-book.html"
    },
    {
        "date": "2017-12-31",
        "title": "Triangle Investing Stocks Real Estate And Crypto Currencies January 8 2018",
        "file": "2017-12-31-triangle-investing-stocks-real-estate-and-crypto-currencies-january-8-2018.html"
    },
    {
        "date": "2015-12-05",
        "title": "What Is Rich",
        "file": "2015-12-05-what-is-rich.html"
    },
    {
        "date": "2019-01-24",
        "title": "Making The Case For Buying A Rental Before Your Own Home",
        "file": "2019-01-24-making-the-case-for-buying-a-rental-before-your-own-home.html"
    },
    {
        "date": "2021-03-04",
        "title": "Qa Is Here Crypto",
        "file": "2021-03-04-qa-is-here-crypto.html"
    },
    {
        "date": "2013-08-16",
        "title": "Controlling Emotions",
        "file": "2013-08-16-controlling-emotions.html"
    },
    {
        "date": "2018-11-18",
        "title": "Millennial Generation Is Going To Be A Group Of Haves And Have Nots",
        "file": "2018-11-18-millennial-generation-is-going-to-be-a-group-of-haves-and-have-nots.html"
    },
    {
        "date": "2013-06-05",
        "title": "The Worst Question In The World",
        "file": "2013-06-05-the-worst-question-in-the-world.html"
    },
    {
        "date": "2014-01-23",
        "title": "Office Politics",
        "file": "2014-01-23-office-politics.html"
    },
    {
        "date": "2013-04-01",
        "title": "Why The Ninety Nine Percent Is Wrong About Wall Street",
        "file": "2013-04-01-why-the-ninety-nine-percent-is-wrong-about-wall-street.html"
    },
    {
        "date": "2017-09-26",
        "title": "Human Nature Will Never Change And How To Profit From It",
        "file": "2017-09-26-human-nature-will-never-change-and-how-to-profit-from-it.html"
    },
    {
        "date": "2020-07-19",
        "title": "Use Technology Or Be Replaced Also Qa Announcement",
        "file": "2020-07-19-use-technology-or-be-replaced-also-qa-announcement.html"
    },
    {
        "date": "2014-03-21",
        "title": "Mba 10 Reasons To Choose Wall Street And Avoid A Start Up",
        "file": "2014-03-21-mba-10-reasons-to-choose-wall-street-and-avoid-a-start-up.html"
    },
    {
        "date": "2017-06-25",
        "title": "You Are Richer Than You Think And What To Do When Youre Set",
        "file": "2017-06-25-you-are-richer-than-you-think-and-what-to-do-when-youre-set.html"
    },
    {
        "date": "2020-08-18",
        "title": "The Human Condition Learning The Truth About People",
        "file": "2020-08-18-the-human-condition-learning-the-truth-about-people.html"
    },
    {
        "date": "2018-05-02",
        "title": "Create A Hard Working Well Rounded Person In A Single Post",
        "file": "2018-05-02-create-a-hard-working-well-rounded-person-in-a-single-post.html"
    },
    {
        "date": "2014-03-17",
        "title": "The Good And Bad Of Anonymous Blogging",
        "file": "2014-03-17-the-good-and-bad-of-anonymous-blogging.html"
    },
    {
        "date": "2014-09-19",
        "title": "Financial Disasters In 10 Simple Equations",
        "file": "2014-09-19-financial-disasters-in-10-simple-equations.html"
    },
    {
        "date": "2020-07-11",
        "title": "Simple Ways To Make Your Life Easier",
        "file": "2020-07-11-simple-ways-to-make-your-life-easier.html"
    },
    {
        "date": "2021-04-10",
        "title": "Launching Substack",
        "file": "2021-04-10-launching-substack.html"
    },
    {
        "date": "2020-11-01",
        "title": "Anticipating Defaults And Bankruptcies A Short Term Outlook",
        "file": "2020-11-01-anticipating-defaults-and-bankruptcies-a-short-term-outlook.html"
    },
    {
        "date": "2014-09-01",
        "title": "Developing Belief Systems",
        "file": "2014-09-01-developing-belief-systems.html"
    },
    {
        "date": "2015-05-03",
        "title": "Is Making Money Psychological",
        "file": "2015-05-03-is-making-money-psychological.html"
    },
    {
        "date": "2012-12-26",
        "title": "You Want To Quit",
        "file": "2012-12-26-you-want-to-quit.html"
    },
    {
        "date": "2014-11-03",
        "title": "Get Out Of The Middle Class",
        "file": "2014-11-03-get-out-of-the-middle-class.html"
    },
    {
        "date": "2017-03-17",
        "title": "The Best Forms Of Passive And Semi Passive Income",
        "file": "2017-03-17-the-best-forms-of-passive-and-semi-passive-income.html"
    },
    {
        "date": "2020-02-01",
        "title": "Why You Will Never Really Retire",
        "file": "2020-02-01-why-you-will-never-really-retire.html"
    },
    {
        "date": "2017-03-13",
        "title": "Is It Time To Take A Risk",
        "file": "2017-03-13-is-it-time-to-take-a-risk.html"
    },
    {
        "date": "2015-01-27",
        "title": "Motivation Is For The Weak",
        "file": "2015-01-27-motivation-is-for-the-weak.html"
    },
    {
        "date": "2021-04-02",
        "title": "Bitclout Looking At The Big Picture Initial Analysis",
        "file": "2021-04-02-bitclout-looking-at-the-big-picture-initial-analysis.html"
    },
    {
        "date": "2019-06-11",
        "title": "Slight Update To Growth Industries And Ways To Be Employed In The Future Qa Announcement As Well",
        "file": "2019-06-11-slight-update-to-growth-industries-and-ways-to-be-employed-in-the-future-qa-announcement-as-well.html"
    },
    {
        "date": "2014-03-03",
        "title": "Investment Banking To A Hedge Fund You Got What It Takes",
        "file": "2014-03-03-investment-banking-to-a-hedge-fund-you-got-what-it-takes.html"
    },
    {
        "date": "2019-06-03",
        "title": "Updated Pattern Recognition And Social Observations",
        "file": "2019-06-03-updated-pattern-recognition-and-social-observations.html"
    },
    {
        "date": "2020-03-11",
        "title": "Its Getting Crazy Out There",
        "file": "2020-03-11-its-getting-crazy-out-there.html"
    },
    {
        "date": "2019-04-19",
        "title": "April Qa Is Here",
        "file": "2019-04-19-april-qa-is-here.html"
    },
    {
        "date": "2013-06-03",
        "title": "Lessons From Growing Up Broke",
        "file": "2013-06-03-lessons-from-growing-up-broke.html"
    },
    {
        "date": "2018-02-11",
        "title": "Building A Recession Proof Life Ten Steps",
        "file": "2018-02-11-building-a-recession-proof-life-ten-steps.html"
    },
    {
        "date": "2020-02-08",
        "title": "Logical View Of The Corona Virus Attempt To Be Balanced",
        "file": "2020-02-08-logical-view-of-the-corona-virus-attempt-to-be-balanced.html"
    },
    {
        "date": "2015-12-29",
        "title": "2015 Review And 2016 Outlook",
        "file": "2015-12-29-2015-review-and-2016-outlook.html"
    },
    {
        "date": "2014-12-17",
        "title": "Frugality Is A Feminine Quality",
        "file": "2014-12-17-frugality-is-a-feminine-quality.html"
    },
    {
        "date": "2014-01-04",
        "title": "The Wolf Of Wall Street Review",
        "file": "2014-01-04-the-wolf-of-wall-street-review.html"
    },
    {
        "date": "2020-06-16",
        "title": "Smile Nod And Agree It May Save Your Life Also Qa Announcement",
        "file": "2020-06-16-smile-nod-and-agree-it-may-save-your-life-also-qa-announcement.html"
    },
    {
        "date": "2021-02-08",
        "title": "Personal Finance",
        "file": "2021-02-08-personal-finance.html"
    },
    {
        "date": "2013-01-14",
        "title": "The Worst Thing You Can Do",
        "file": "2013-01-14-the-worst-thing-you-can-do.html"
    },
    {
        "date": "2018-10-20",
        "title": "How To Hire Or Buy The Best Solution",
        "file": "2018-10-20-how-to-hire-or-buy-the-best-solution.html"
    },
    {
        "date": "2017-11-12",
        "title": "Crypto Currency A Basic Introduction The Future",
        "file": "2017-11-12-crypto-currency-a-basic-introduction-the-future.html"
    },
    {
        "date": "2019-06-14",
        "title": "Wallstreetplayboys.Com",
        "file": "2019-06-14-wallstreetplayboys.com.html"
    },
    {
        "date": "2020-03-07",
        "title": "Market Chaos Another Crisis Another Opportunity",
        "file": "2020-03-07-market-chaos-another-crisis-another-opportunity.html"
    },
    {
        "date": "2015-02-08",
        "title": "Money Making Machine",
        "file": "2015-02-08-money-making-machine.html"
    },
    {
        "date": "2014-03-05",
        "title": "International Playboy Preparation And Destinations",
        "file": "2014-03-05-international-playboy-preparation-and-destinations.html"
    },
    {
        "date": "2014-06-09",
        "title": "A Detailed Look At Financial Institutions Group Fig",
        "file": "2014-06-09-a-detailed-look-at-financial-institutions-group-fig.html"
    },
    {
        "date": "2016-12-18",
        "title": "Investment Banking Compensation 2016",
        "file": "2016-12-18-investment-banking-compensation-2016.html"
    },
    {
        "date": "2017-10-03",
        "title": "How To Operate In Airports And An Important Announcement",
        "file": "2017-10-03-how-to-operate-in-airports-and-an-important-announcement.html"
    },
    {
        "date": "2014-06-25",
        "title": "10 Ways To Become Exceptional Starting Now",
        "file": "2014-06-25-10-ways-to-become-exceptional-starting-now.html"
    },
    {
        "date": "2020-09-13",
        "title": "Looking At The Bright Side Of The Lock Down",
        "file": "2020-09-13-looking-at-the-bright-side-of-the-lock-down.html"
    },
    {
        "date": "2013-07-16",
        "title": "Stand Out As A Non Target Recruiting Into Wall Street",
        "file": "2013-07-16-stand-out-as-a-non-target-recruiting-into-wall-street.html"
    },
    {
        "date": "2018-12-20",
        "title": "2018 Investment Banking Compensation And Qa Announcement",
        "file": "2018-12-20-2018-investment-banking-compensation-and-qa-announcement.html"
    },
    {
        "date": "2020-08-02",
        "title": "Crystal Clear Structural Changes After Covid",
        "file": "2020-08-02-crystal-clear-structural-changes-after-covid.html"
    },
    {
        "date": "2013-06-12",
        "title": "Personal Income Taxes Why We Think You Should Be Liquid",
        "file": "2013-06-12-personal-income-taxes-why-we-think-you-should-be-liquid.html"
    },
    {
        "date": "2014-03-06",
        "title": "Attention To Detial Is Overrated",
        "file": "2014-03-06-attention-to-detial-is-overrated.html"
    },
    {
        "date": "2018-03-26",
        "title": "Great Businesses From Expensive To Cheap",
        "file": "2018-03-26-great-businesses-from-expensive-to-cheap.html"
    },
    {
        "date": "2013-03-07",
        "title": "Are You Really Maximizing Your Time",
        "file": "2013-03-07-are-you-really-maximizing-your-time.html"
    },
    {
        "date": "2020-02-06",
        "title": "This Blog Apparently Has Female Readers",
        "file": "2020-02-06-this-blog-apparently-has-female-readers.html"
    },
    {
        "date": "spending.h",
        "title": "Ml",
        "file": "spending.html"
    },
    {
        "date": "2015-03-22",
        "title": "Uncovering The Truth",
        "file": "2015-03-22-uncovering-the-truth.html"
    },
    {
        "date": "2019-07-16",
        "title": "Success",
        "file": "2019-07-16-success.html"
    },
    {
        "date": "2012-12-29",
        "title": "Game By Ethnicity 2",
        "file": "2012-12-29-game-by-ethnicity-2.html"
    },
    {
        "date": "2013-04-12",
        "title": "Top Ten Reasons You Are Broke",
        "file": "2013-04-12-top-ten-reasons-you-are-broke.html"
    },
    {
        "date": "2016-03-12",
        "title": "Office Politics It Only Gets Worse",
        "file": "2016-03-12-office-politics-it-only-gets-worse.html"
    },
    {
        "date": "2019-06-24",
        "title": "Wallstreetplayboys.Com",
        "file": "2019-06-24-wallstreetplayboys.com.html"
    },
    {
        "date": "2018-02-20",
        "title": "Avoiding The Pitfalls Of The Millionaire Life",
        "file": "2018-02-20-avoiding-the-pitfalls-of-the-millionaire-life.html"
    },
    {
        "date": "2013-02-06",
        "title": "Networking Jobs And A Social Circle",
        "file": "2013-02-06-networking-jobs-and-a-social-circle.html"
    },
    {
        "date": "2013-02-16",
        "title": "The Most Common Excuse",
        "file": "2013-02-16-the-most-common-excuse.html"
    },
    {
        "date": "2019-05-16",
        "title": "Extreme Prioritization When Traveling Like A Mad Man",
        "file": "2019-05-16-extreme-prioritization-when-traveling-like-a-mad-man.html"
    },
    {
        "date": "2014-02-12",
        "title": "Investing Priorities",
        "file": "2014-02-12-investing-priorities.html"
    },
    {
        "date": "2014-12-22",
        "title": "You Are Taught To Be Poor",
        "file": "2014-12-22-you-are-taught-to-be-poor.html"
    },
    {
        "date": "2013-06-08",
        "title": "The Solution To Identity Security",
        "file": "2013-06-08-the-solution-to-identity-security.html"
    },
    {
        "date": "2015-05-31",
        "title": "Things To Know For Your Thirties",
        "file": "2015-05-31-things-to-know-for-your-thirties.html"
    },
    {
        "date": "2019-04-09",
        "title": "List Of Items To Be Aware Of For Your 30S",
        "file": "2019-04-09-list-of-items-to-be-aware-of-for-your-30s.html"
    },
    {
        "date": "2014-03-13",
        "title": "2014 Book Recommendations",
        "file": "2014-03-13-2014-book-recommendations.html"
    },
    {
        "date": "2019-05-20",
        "title": "May 2019 Qa",
        "file": "2019-05-20-may-2019-qa.html"
    },
    {
        "date": "2014-02-09",
        "title": "Managing Life Decisions To Make 100K A Year",
        "file": "2014-02-09-managing-life-decisions-to-make-100k-a-year.html"
    },
    {
        "date": "2013-01-25",
        "title": "Myths About Wall Street",
        "file": "2013-01-25-myths-about-wall-street.html"
    },
    {
        "date": "2018-03-12",
        "title": "A New Lifestyle After Financial Independence",
        "file": "2018-03-12-a-new-lifestyle-after-financial-independence.html"
    },
    {
        "date": "2016-09-26",
        "title": "Savings Rates Are Worthless And What Real Net Worth Is",
        "file": "2016-09-26-savings-rates-are-worthless-and-what-real-net-worth-is.html"
    },
    {
        "date": "2013-05-13",
        "title": "Hacking Your 401K",
        "file": "2013-05-13-hacking-your-401k.html"
    },
    {
        "date": "2017-06-03",
        "title": "Creating Luck",
        "file": "2017-06-03-creating-luck.html"
    }
]